spinloader/__init__.py
spinloader/colors.py
spinloader/exceptions.py
spinloader/spinloader.py
spinloader/threads.py
Spinloader-0.0.1.dist-info/LICENSE
Spinloader-0.0.1.dist-info/METADATA
Spinloader-0.0.1.dist-info/WHEEL
Spinloader-0.0.1.dist-info/top_level.txt
Spinloader-0.0.1.dist-info/RECORD
