Metadata-Version: 2.1
Name: Spinloader
Version: 0.0.1
Summary: A CLI animator that does a little more than just render animations
License-File: LICENSE
